slimify/__init__.py
slimify-0.0.1.dist-info/METADATA
slimify-0.0.1.dist-info/WHEEL
slimify-0.0.1.dist-info/licenses/LICENSE
slimify-0.0.1.dist-info/RECORD
